tailscale/__init__.py
tailscale/exceptions.py
tailscale/models.py
tailscale/py.typed
tailscale/storage.py
tailscale/tailscale.py
tailscale_fixed-0.8.0.dist-info/METADATA
tailscale_fixed-0.8.0.dist-info/WHEEL
tailscale_fixed-0.8.0.dist-info/licenses/LICENSE.md
tailscale_fixed-0.8.0.dist-info/RECORD
