Metadata-Version: 2.4
Name: tailscale-fixed
Version: 0.8.0
Summary: Asynchronous client for the Tailscale API. [[[ This is a fork, that contains the unmerged fixes from the original repo. ]]]
License: MIT
License-File: LICENSE.md
Keywords: tailscale,vpn,wireguard,api,async,client
Author: Franck Nijhof
Author-email: opensource@frenck.dev
Maintainer: Laszlo Magyar
Maintainer-email: lmagyar1973@gmail.com
Requires-Python: >=3.11,<4.0
Classifier: Development Status :: 5 - Production/Stable
Classifier: Framework :: AsyncIO
Classifier: Intended Audience :: Developers
Classifier: License :: OSI Approved :: MIT License
Classifier: Natural Language :: English
Classifier: Programming Language :: Python :: 3
Classifier: Programming Language :: Python :: 3.11
Classifier: Programming Language :: Python :: 3.12
Classifier: Programming Language :: Python :: 3.13
Classifier: Programming Language :: Python :: 3.14
Classifier: Topic :: Software Development :: Libraries :: Python Modules
Requires-Dist: aiohttp (>=3.0.0)
Requires-Dist: mashumaro (>=3.10)
Requires-Dist: orjson (>=3.9.8)
Requires-Dist: yarl (>=1.6.0)
Project-URL: Bug Tracker, https://github.com/lmagyar/python-tailscale/issues
Project-URL: Changelog, https://github.com/lmagyar/python-tailscale/releases
Project-URL: Documentation, https://github.com/lmagyar/python-tailscale
Project-URL: Homepage, https://github.com/lmagyar/python-tailscale
Project-URL: Repository, https://github.com/lmagyar/python-tailscale
